com2fun/__init__.py
com2fun/composer/__init__.py
com2fun/composer/python_interpreter/__init__.py
com2fun/composer/python_interpreter/python_interpreter_gen_prompts.py
com2fun/func_def.py
com2fun/llm_utils.py
com2fun/simulated_function/__init__.py
com2fun/simulated_function/abstract.py
com2fun/simulated_function/anthropic.py
com2fun/simulated_function/openai.py
com2fun/simulated_function/simplellmsfbase.py
com2fun-0.1.10.dist-info/LICENSE
com2fun-0.1.10.dist-info/METADATA
com2fun-0.1.10.dist-info/WHEEL
com2fun-0.1.10.dist-info/RECORD
