Metadata-Version: 2.1
Name: com2fun
Version: 0.1.10
Summary: Transform document into function
Author: Zhengmian Hu
Author-email: huzhengmian@gmail.com
Requires-Python: >=3.8
Classifier: Programming Language :: Python :: 3
Classifier: Programming Language :: Python :: 3.8
Classifier: Programming Language :: Python :: 3.9
Classifier: Programming Language :: Python :: 3.10
Classifier: Programming Language :: Python :: 3.11
Provides-Extra: all
Provides-Extra: anthropic
Requires-Dist: anthropic (>=0.18.1) ; extra == "anthropic" or extra == "all"
Requires-Dist: openai (>=1.9.0)
